MANIFEST.in
README.rst
develop_requirements.txt
requirements.txt
setup.py
test_requirements.txt
btctxstore/__init__.py
btctxstore/api.py
btctxstore/common.py
btctxstore/control.py
btctxstore/deserialize.py
btctxstore/exceptions.py
btctxstore/serialize.py
btctxstore/validate.py
btctxstore/version.py
btctxstore.egg-info/PKG-INFO
btctxstore.egg-info/SOURCES.txt
btctxstore.egg-info/dependency_links.txt
btctxstore.egg-info/not-zip-safe
btctxstore.egg-info/requires.txt
btctxstore.egg-info/top_level.txt
btctxstore/services/__init__.py
btctxstore/services/automatic.py
btctxstore/services/bitcoind.py
btctxstore/services/blockexplorer.py
btctxstore/services/insight.py
btctxstore/services/interface.py
tests/__init__.py
tests/deserialize.py
tests/fixtures.json
tests/api/__init__.py
tests/api/confirms.py
tests/api/create_key.py
tests/api/create_wallet.py
tests/api/get_address.py
tests/api/get_key.py
tests/api/get_transactions.py
tests/api/other.py
tests/api/validate_wallet.py
tests/api/verify_signature.py