Metadata-Version: 1.1
Name: btctxstore
Version: 4.8.0
Summary: Library to read/write data to bitcoin transaction outputs.
Home-page: https://github.com/F483/btctxstore/
Author: Fabian Barkhau
Author-email: fabian.barkhau@gmail.com
License: MIT
Download-URL: https://pypi.python.org/packages/source/a/btctxstore/btctxstore-4.8.0.tar.gz
Keywords: Bitcoin,OP_RETURN,store,tx,transaction
Platform: UNKNOWN
Classifier: Development Status :: 4 - Beta
Classifier: Intended Audience :: Developers
Classifier: License :: OSI Approved :: MIT License
Classifier: Operating System :: OS Independent
Classifier: Programming Language :: Python
Classifier: Programming Language :: Python :: 2
Classifier: Programming Language :: Python :: 2.7
Classifier: Programming Language :: Python :: 3
Classifier: Programming Language :: Python :: 3.3
Classifier: Programming Language :: Python :: 3.4
Classifier: Topic :: Software Development :: Libraries :: Python Modules
